edk2basetools/GNUmakefile
edk2basetools/Makefile
edk2basetools/__init__.py
edk2basetools/basetool_tiano_python_path_env.yaml
edk2basetools/sitecustomize.py
edk2basetools/AmlToC/AmlToC.py
edk2basetools/AutoGen/AutoGen.py
edk2basetools/AutoGen/AutoGenWorker.py
edk2basetools/AutoGen/BuildEngine.py
edk2basetools/AutoGen/DataPipe.py
edk2basetools/AutoGen/GenC.py
edk2basetools/AutoGen/GenDepex.py
edk2basetools/AutoGen/GenMake.py
edk2basetools/AutoGen/GenPcdDb.py
edk2basetools/AutoGen/GenVar.py
edk2basetools/AutoGen/IdfClassObject.py
edk2basetools/AutoGen/IncludesAutoGen.py
edk2basetools/AutoGen/InfSectionParser.py
edk2basetools/AutoGen/ModuleAutoGen.py
edk2basetools/AutoGen/ModuleAutoGenHelper.py
edk2basetools/AutoGen/PlatformAutoGen.py
edk2basetools/AutoGen/StrGather.py
edk2basetools/AutoGen/UniClassObject.py
edk2basetools/AutoGen/ValidCheckingInfoObject.py
edk2basetools/AutoGen/WorkspaceAutoGen.py
edk2basetools/AutoGen/__init__.py
edk2basetools/BPDG/BPDG.py
edk2basetools/BPDG/GenVpd.py
edk2basetools/BPDG/StringTable.py
edk2basetools/BPDG/__init__.py
edk2basetools/Capsule/GenerateCapsule.py
edk2basetools/Capsule/GenerateWindowsDriver.py
edk2basetools/Capsule/WindowsCapsuleSupportHelper.py
edk2basetools/Common/BuildToolError.py
edk2basetools/Common/BuildVersion.py
edk2basetools/Common/DataType.py
edk2basetools/Common/EdkLogger.py
edk2basetools/Common/Expression.py
edk2basetools/Common/GlobalData.py
edk2basetools/Common/LongFilePathOs.py
edk2basetools/Common/LongFilePathOsPath.py
edk2basetools/Common/LongFilePathSupport.py
edk2basetools/Common/Misc.py
edk2basetools/Common/MultipleWorkspace.py
edk2basetools/Common/Parsing.py
edk2basetools/Common/RangeExpression.py
edk2basetools/Common/StringUtils.py
edk2basetools/Common/TargetTxtClassObject.py
edk2basetools/Common/ToolDefClassObject.py
edk2basetools/Common/VariableAttributes.py
edk2basetools/Common/VpdInfoFile.py
edk2basetools/Common/__init__.py
edk2basetools/Common/caching.py
edk2basetools/Common/Edk2/__init__.py
edk2_basetools-0.1.53.dist-info/LICENSE
edk2_basetools-0.1.53.dist-info/METADATA
edk2_basetools-0.1.53.dist-info/WHEEL
edk2_basetools-0.1.53.dist-info/entry_points.txt
edk2_basetools-0.1.53.dist-info/top_level.txt
edk2_basetools-0.1.53.dist-info/RECORD
