Metadata-Version: 2.1
Name: edk2-basetools
Version: 0.1.53
Summary: Python BaseTools supporting UEFI EDK2 firmware development
Author-email: TianoCore EDK2-BaseTools Team <devel@edk2.groups.io>
Maintainer-email: Liming Gao <gaoliming@byosoft.com.cn>, Rebecca Cran <rebecca@bsdio.com>
License: Copyright (c) 2019, TianoCore and contributors.  All rights reserved.
Project-URL: homepage, https://github.com/tianocore/edk2-basetools
Project-URL: issues, https://github.com/tianocore/edk2-basetools/issues
Classifier: Programming Language :: Python :: 3
Classifier: License :: OSI Approved :: BSD License
Classifier: Operating System :: OS Independent
Classifier: Development Status :: 4 - Beta
Classifier: Intended Audience :: Developers
Requires-Python: >=3.10
License-File: LICENSE
Requires-Dist: edk2-pytool-library >=0.20.0
Requires-Dist: antlr4-python3-runtime >=4.7.1
Provides-Extra: publish
Requires-Dist: setuptools ; extra == 'publish'
Requires-Dist: build ; extra == 'publish'
